coinbaseadvanced/__init__.py
coinbaseadvanced/client.py
coinbaseadvanced/client_websocket.py
coinbaseadvanced/utils.py
coinbaseadvanced/models/__init__.py
coinbaseadvanced/models/accounts.py
coinbaseadvanced/models/common.py
coinbaseadvanced/models/error.py
coinbaseadvanced/models/fees.py
coinbaseadvanced/models/futures.py
coinbaseadvanced/models/market_data.py
coinbaseadvanced/models/orders.py
coinbaseadvanced/models/portfolios.py
coinbaseadvanced/models/products.py
tests/fixtures/__init__.py
tests/fixtures/fixtures.py
coinbaseadvanced-1.2.0.dist-info/LICENSE
coinbaseadvanced-1.2.0.dist-info/METADATA
coinbaseadvanced-1.2.0.dist-info/WHEEL
coinbaseadvanced-1.2.0.dist-info/top_level.txt
coinbaseadvanced-1.2.0.dist-info/RECORD
