Metadata-Version: 2.1
Name: coinbaseadvanced
Version: 1.2.0
Summary: Coinbase Advanced Trade API client library.
Home-page: https://github.com/KmiQ/coinbase-advanced-python/
Download-URL: https://github.com/KmiQ/coinbase-advanced-python/archive/refs/tags/1.2.0.tar.gz
Author: Camilo Quintas
Author-email: kmiloc89@gmail.com
License: MIT
Keywords: api,coinbase,bitcoin,client,crypto
Classifier: Development Status :: 5 - Production/Stable
Classifier: Intended Audience :: Developers
Classifier: Intended Audience :: Financial and Insurance Industry
Classifier: Natural Language :: English
Classifier: License :: OSI Approved :: MIT License
Classifier: Programming Language :: Python :: 3.8
Classifier: Operating System :: OS Independent
Classifier: Topic :: Software Development :: Libraries :: Python Modules
License-File: LICENSE
Requires-Dist: cfgv ==3.3.1
Requires-Dist: cryptography ==42.0.4
Requires-Dist: PyJWT ==2.8.0
Requires-Dist: requests ==2.32.0
Requires-Dist: rfc3986 ==2.0.0
Requires-Dist: websocket-client ==1.8.0
